SivParseHLK/XMLtoCSVConvert.py
SivParseHLK-1.0.2.dist-info/LICENSE.txt
SivParseHLK-1.0.2.dist-info/METADATA
SivParseHLK-1.0.2.dist-info/WHEEL
SivParseHLK-1.0.2.dist-info/top_level.txt
SivParseHLK-1.0.2.dist-info/RECORD
