Metadata-Version: 2.1
Name: SivParseHLK
Version: 1.0.2
Summary: Convert HLK test result logs from XML format  to csv format
Home-page: UNKNOWN
Author: Komal
Author-email: komalpreetx.kaur@intel.com
License: Commercial
Platform: UNKNOWN
